README
setup.py
cfirst/__init__.py
cfirst/cfirst.py
cfirst.egg-info/PKG-INFO
cfirst.egg-info/SOURCES.txt
cfirst.egg-info/dependency_links.txt
cfirst.egg-info/entry_points.txt
cfirst.egg-info/top_level.txt