Metadata-Version: 1.0
Name: cfirst
Version: 0.1.0
Summary: Tookit for c program beginner.
Home-page: https://www.gitbook.com/book/qorzj/first-book-of-coding
Author: qorzj
Author-email: inull@qq.com
License: MIT
Keywords: cfirst
Platform: any
